lds_gen/__init__.py
lds_gen/ilds.py
lds_gen/lds.py
lds_gen/skeleton.py
lds_gen-0.2.dist-info/licenses/LICENSE.txt
lds_gen-0.2.dist-info/METADATA
lds_gen-0.2.dist-info/WHEEL
lds_gen-0.2.dist-info/top_level.txt
lds_gen-0.2.dist-info/RECORD
