Metadata-Version: 2.4
Name: lds-gen
Version: 0.2
Summary: Low Discrepancy Sequence Generation
Home-page: https://luk036.github.io/lds-gen/
Author: Wai-Shing Luk
Author-email: luk036@gmail.com
License: MIT
Project-URL: Documentation, https://pyscaffold.org/
Platform: any
Classifier: Development Status :: 4 - Beta
Classifier: Programming Language :: Python
License-File: LICENSE.txt
Requires-Dist: importlib-metadata; python_version < "3.9"
Provides-Extra: testing
Requires-Dist: setuptools; extra == "testing"
Requires-Dist: pytest; extra == "testing"
Requires-Dist: pytest-cov; extra == "testing"
Dynamic: license-file
